quantipy/__init__.py
quantipy/version.py
quantipy/core/__init__.py
quantipy/core/batch.py
quantipy/core/cache.py
quantipy/core/chain.py
quantipy/core/cluster.py
quantipy/core/dataset.py
quantipy/core/link.py
quantipy/core/options.py
quantipy/core/rules.py
quantipy/core/stack.py
quantipy/core/view.py
quantipy/core/builds/__init__.py
quantipy/core/builds/excel/__init__.py
quantipy/core/builds/excel/excel_painter.py
quantipy/core/builds/excel/formats/__init__.py
quantipy/core/builds/excel/formats/xlsx_formats.py
quantipy/core/builds/powerpoint/__init__.py
quantipy/core/builds/powerpoint/add_shapes.py
quantipy/core/builds/powerpoint/helpers.py
quantipy/core/builds/powerpoint/pptx_painter.py
quantipy/core/builds/powerpoint/transformations.py
quantipy/core/builds/powerpoint/visual_editor.py
quantipy/core/builds/powerpoint/templates/__init__.py
quantipy/core/helpers/__init__.py
quantipy/core/helpers/constants.py
quantipy/core/helpers/functions.py
quantipy/core/quantify/__init__.py
quantipy/core/quantify/engine.py
quantipy/core/srv/__init__.py
quantipy/core/srv/core.py
quantipy/core/srv/handlers.py
quantipy/core/srv/servers.py
quantipy/core/tools/__init__.py
quantipy/core/tools/audit.py
quantipy/core/tools/qp_decorators.py
quantipy/core/tools/dp/__init__.py
quantipy/core/tools/dp/io.py
quantipy/core/tools/dp/prep.py
quantipy/core/tools/dp/query.py
quantipy/core/tools/dp/ascribe/__init__.py
quantipy/core/tools/dp/ascribe/reader.py
quantipy/core/tools/dp/decipher/__init__.py
quantipy/core/tools/dp/decipher/reader.py
quantipy/core/tools/dp/dimensions/__init__.py
quantipy/core/tools/dp/dimensions/_create_ddf.dms
quantipy/core/tools/dp/dimensions/dimlabels.py
quantipy/core/tools/dp/dimensions/map_dim_qp_languages.xlsx
quantipy/core/tools/dp/dimensions/reader.py
quantipy/core/tools/dp/dimensions/writer.py
quantipy/core/tools/dp/forsta/__init__.py
quantipy/core/tools/dp/forsta/api_requests.py
quantipy/core/tools/dp/forsta/helpers.py
quantipy/core/tools/dp/forsta/languages_file.py
quantipy3-0.2.15.dist-info/LICENSE.txt
quantipy3-0.2.15.dist-info/METADATA
quantipy3-0.2.15.dist-info/WHEEL
quantipy3-0.2.15.dist-info/top_level.txt
quantipy3-0.2.15.dist-info/RECORD
